tests/__init__.py
tests/test_basic.py
tests/test_script.py
tests/test_wpfunction.py
tests/test_wpignore.py
tests/test_wplist.py
tests/test_wpname.py
tests/test_wpnugget.py
tests/test_wpoptional.py
weakscraper/__init__.py
weakscraper/exceptions.py
weakscraper/htmlparser.py
weakscraper/resulttree.py
weakscraper/template.py
weakscraper/templateparser.py
weakscraper/weakscraper.py
weakscraper-0.0.1.dist-info/DESCRIPTION.rst
weakscraper-0.0.1.dist-info/METADATA
weakscraper-0.0.1.dist-info/RECORD
weakscraper-0.0.1.dist-info/WHEEL
weakscraper-0.0.1.dist-info/metadata.json
weakscraper-0.0.1.dist-info/top_level.txt
