Metadata-Version: 2.0
Name: weakscraper
Version: 0.0.1
Summary: HTML scraper with templates
Home-page: https://github.com/michelbl/weakscraper
Author: Michel Blancard
Author-email: UNKNOWN
License: MIT
Keywords: parser scraper HTML template
Platform: UNKNOWN
Classifier: Development Status :: 3 - Alpha
Classifier: License :: OSI Approved :: MIT License
Classifier: Programming Language :: Python :: 3
